zcoinbase/__init__.py
zcoinbase/authenticated_client.py
zcoinbase/coinbase_auth.py
zcoinbase/coinbase_order_book.py
zcoinbase/historical_data_downloader.py
zcoinbase/public_client.py
zcoinbase/rest_client.py
zcoinbase/util.py
zcoinbase/websocket_client.py
zcoinbase/internal/__init__.py
zcoinbase/internal/rate_limited_execution_queue.py
zcoinbase-0.0.9.dist-info/LICENSE
zcoinbase-0.0.9.dist-info/METADATA
zcoinbase-0.0.9.dist-info/WHEEL
zcoinbase-0.0.9.dist-info/top_level.txt
zcoinbase-0.0.9.dist-info/RECORD
